LICENSE
MANIFEST.in
README.md
mjpy.py
pyproject.toml
requirments.py
setup.cfg
setup.py
MjPy.egg-info/PKG-INFO
MjPy.egg-info/SOURCES.txt
MjPy.egg-info/dependency_links.txt
MjPy.egg-info/entry_points.txt
MjPy.egg-info/top_level.txt
MjPy-0.1.dist-info/LICENSE
MjPy-0.1.dist-info/METADATA
MjPy-0.1.dist-info/WHEEL
MjPy-0.1.dist-info/entry_points.txt
MjPy-0.1.dist-info/top_level.txt
MjPy-0.1.dist-info/RECORD
